{"better": 2, "day": 2, "box": 4, "ceo": 2, "aaron": 2, "leviea": 1, "good": 2, "second": 3, "quarter": 3, "showing": 1, "yesterday": 1, "set": 1, "earnings": 3, "public": 1, "company": 2, "sending": 1, "stock": 2, "price": 1, "wall": 3, "streetthe": 1, "newsrevenue": 1, "yearonyear": 3, "millionbillings": 1, "million": 1, "new": 1, "customer": 8, "added": 1, "quartertotal": 1, "headcount": 1, "bad": 1, "newsnet": 1, "loss": 1, "millionnegative": 1, "operating": 1, "cash": 2, "flow": 2, "millionstill": 1, "way": 2, "many": 1, "using": 1, "free": 2, "serviceon": 1, "number": 2, "highlighted": 1, "increasing": 1, "big": 3, "ticket": 2, "deal": 4, "enterprise": 1, "hewlettpackard": 1, "chevron": 1, "halliburton": 1, "nationwideit": 1, "also": 1, "closed": 1, "largest": 1, "federal": 1, "government": 1, "date": 1, "may": 1, "signed": 1, "u": 1, "department": 1, "justiceaccording": 1, "name": 2, "indicative": 1, "success": 1, "pushing": 1, "enterpriseduring": 1, "worth": 1, "thant": 1, "five": 1, "excess": 1, "levie": 1, "spent": 1, "lot": 1, "time": 1, "firm": 1, "first": 2, "report": 1, "trying": 1, "explain": 1, "clarify": 1, "allocation": 1, "confused": 1, "street": 2, "firmer": 1, "ground": 1, "herewe": 1, "winning": 1, "bigger": 1, "extending": 1, "reach": 1, "highly": 1, "regulated": 1, "industry": 1, "securityconscious": 1, "segment": 1, "marketmy": 1, "takea": 1, "much": 1, "go": 1, "still": 2, "revenue": 1, "growth": 1, "impressive": 1, "compared": 1, "rate": 1, "reported": 1, "last": 1, "year": 2, "increase": 1, "paying": 2, "encouraging": 1, "there": 1, "user": 1, "base": 1, "thats": 1, "servicelevie": 1, "reckons": 1, "positive": 1, "end": 1, "next": 1, "fiscal": 1, "profitable": 1, "increasingly": 1, "competitive": 1, "market": 1, "sector": 1, "going": 1, "need": 1, "see": 1, "hold": 1, "nerveread": 1, "cloud": 1, "platform": 1, "infrastructure": 1, "architecturecollaboration": 1, "sharing": 1, "digital": 1, "productivitycrm": 1, "experiencedigital": 1, "content": 1, "marketingsocial": 1}