{"year": 3, "history": 1, "business": 3, "oriented": 1, "around": 2, "catalog": 1, "selling": 1, "fashion": 2, "retailer": 3, "n": 2, "brown": 2, "group": 3, "midst": 1, "transformation": 2, "program": 1, "refresh": 1, "system": 11, "digital": 4, "age": 1, "called": 1, "fit": 3, "future": 1, "twoyear": 1, "project": 1, "move": 2, "cloud": 8, "replace": 1, "aging": 1, "application": 2, "longer": 1, "purposethe": 1, "portfolio": 1, "home": 1, "shopping": 2, "brand": 2, "include": 1, "jd": 1, "williams": 1, "simply": 2, "jacamo": 1, "aimed": 1, "consumer": 1, "poorly": 1, "served": 2, "mainstream": 1, "older": 1, "woman": 1, "taking": 1, "larger": 1, "employing": 1, "people": 1, "lselisted": 1, "company": 2, "operates": 1, "largely": 1, "uk": 1, "presence": 1, "ireland": 1, "continental": 1, "europe": 1, "u": 3, "revenue": 1, "last": 3, "financial": 3, "million": 2, "bn": 1, "twothirds": 1, "sale": 1, "online": 1, "rest": 1, "phone": 1, "mail": 1, "order": 1, "recentlyopened": 1, "storesthe": 1, "need": 4, "radical": 1, "overhaul": 1, "support": 1, "multichannel": 1, "ambition": 1, "say": 4, "lee": 2, "harris": 3, "programme": 1, "director": 1, "projectto": 1, "change": 3, "content": 1, "website": 2, "required": 1, "code": 2, "deployment": 1, "took": 1, "hoursthe": 1, "contact": 1, "center": 1, "view": 1, "customer": 3, "basket": 1, "greenscreen": 1, "service": 2, "applicationthe": 1, "platform": 7, "didnt": 1, "allow": 1, "scale": 2, "international": 1, "marketsthe": 1, "strategy": 1, "putting": 1, "right": 1, "consisted": 1, "deploying": 1, "modern": 1, "new": 7, "moving": 1, "entire": 1, "infrastructure": 2, "backend": 1, "oracle": 2, "retail": 1, "suite": 1, "fusion": 1, "financials": 1, "hr": 1, "moved": 1, "ibmmanaged": 1, "private": 1, "hybris": 1, "ecommerce": 4, "run": 1, "ibm": 1, "softlayer": 3, "public": 1, "credit": 3, "scoring": 1, "powercurve": 1, "form": 1, "core": 1, "allnew": 1, "applicationagiledeliverythe": 1, "accompanied": 1, "switch": 1, "development": 2, "mindset": 1, "tune": 1, "cloudnative": 1, "environment": 1, "devops": 3, "model": 3, "continuous": 1, "delivery": 2, "transformed": 1, "ability": 1, "manage": 1, "harrisweve": 1, "got": 1, "truly": 1, "agile": 1, "deploy": 1, "minute": 1, "start": 1, "quickly": 1, "going": 3, "important": 2, "hit": 1, "peak": 2, "daysthe": 1, "full": 1, "already": 1, "live": 1, "european": 1, "launch": 1, "next": 1, "pause": 1, "season": 1, "pageviews": 1, "black": 1, "friday": 1, "roll": 1, "flagship": 1, "market": 1, "early": 1, "experience": 1, "using": 1, "built": 1, "confidence": 1, "de": 1, "facto": 1, "choice": 1, "hosting": 1, "harrisone": 1, "hardlearned": 1, "lesson": 1, "host": 1, "integration": 2, "server": 1, "closer": 1, "originally": 1, "planned": 2, "hindsight": 1, "would": 1, "better": 1, "outset": 2, "explainsto": 1, "get": 1, "performance": 1, "latency": 1, "middleware": 3, "onto": 1, "learning": 1, "difficult": 1, "middle": 1, "programif": 1, "wed": 2, "realised": 1, "much": 1, "wanted": 1, "put": 1, "made": 1, "different": 2, "choicesbusiness": 1, "colleague": 2, "also": 1, "make": 1, "adjustment": 1, "inhouse": 1, "team": 1, "embraced": 1, "rapidcycling": 1, "still": 1, "adapting": 1, "speed": 4, "functionality": 1, "introduced": 1, "harristhe": 1, "developer": 1, "love": 1, "difficulty": 1, "losing": 1, "controlmy": 1, "takeanother": 1, "bite": 1, "bullet": 1, "replaces": 1, "ageing": 1, "adaptable": 1, "commerce": 1, "infrastructureone": 1, "takeaway": 2, "story": 1, "concern": 1, "decision": 1, "relocate": 1, "bimodal": 1, "landscape": 1, "becomes": 2, "gearbox": 2, "allows": 1, "running": 1, "synchronize": 1, "effectively": 1, "youre": 1, "engage": 1, "maintaining": 1, "slowerpaced": 1, "backoffice": 1, "highperformance": 1, "critical": 1, "component": 1, "ensure": 1, "smooth": 1, "operationanother": 1, "understand": 1, "technology": 1, "replacement": 1, "repercussion": 1, "effected": 1, "demand": 1, "agilemethodologiesthroughout": 1, "businessimage": 1, "shopfront": 1, "groupdisclosure": 1, "speaking": 1, "ibms": 1, "emea": 1, "analyst": 1, "summit": 1, "london": 1, "month": 1, "sap": 1, "diginomica": 1, "premier": 1, "partner": 1, "time": 1, "writing": 1, "read": 1, "architecturedevops": 1, "nosql": 1, "open": 1, "source": 1, "stackretail": 1, "omnichanneluse": 1, "case": 1}