{"untold": 1, "story": 2, "behind": 2, "oracle": 19, "secondquarter": 1, "result": 1, "growing": 2, "customer": 4, "momentum": 1, "towards": 2, "cloud": 17, "apps": 2, "particular": 1, "erp": 9, "need": 3, "modernize": 2, "digitally": 1, "transform": 1, "driving": 1, "organization": 2, "move": 3, "core": 1, "enterprise": 6, "application": 10, "cloudfor": 1, "example": 1, "well": 3, "year": 2, "familyowned": 1, "managed": 1, "ice": 1, "cream": 1, "business": 5, "picked": 1, "hcm": 6, "human": 1, "resource": 1, "payroll": 2, "technologyaccording": 1, "jasen": 1, "heaton": 1, "director": 2, "logical": 2, "place": 2, "begin": 1, "journey": 2, "cloudwe": 1, "knew": 1, "time": 1, "start": 3, "moving": 1, "decided": 3, "bitesized": 1, "fashion": 1, "hr": 3, "system": 3, "old": 1, "labor": 1, "intensive": 1, "lot": 1, "manual": 1, "process": 2, "chose": 1, "forward": 1, "cloudempowering": 1, "hourly": 1, "worker": 1, "mobile": 1, "access": 1, "relevant": 1, "benefit": 1, "function": 1, "one": 1, "huge": 1, "driver": 1, "deploy": 1, "want": 1, "folk": 1, "productive": 1, "logistics": 1, "assembly": 1, "work": 1, "production": 1, "floor": 1, "delivered": 1, "premisecloud": 1, "drive": 3, "change": 6, "western": 4, "digitalcomputer": 1, "storage": 1, "manufacturer": 1, "digital": 5, "acquiring": 1, "sandisk": 1, "hgst": 1, "faced": 1, "challenge": 1, "rationalizing": 2, "three": 2, "fortune": 1, "size": 1, "onpremises": 1, "needed": 2, "modern": 1, "suite": 1, "bestinclass": 1, "would": 2, "enable": 2, "enhance": 1, "experience": 1, "achieve": 3, "competitive": 1, "advantage": 1, "improving": 1, "employee": 1, "productivity": 2, "steve": 1, "phillpott": 1, "cio": 1, "explainsthe": 1, "large": 1, "legacy": 1, "associated": 1, "gave": 1, "u": 2, "unique": 1, "opportunity": 1, "two": 1, "third": 1, "undergo": 1, "matter": 1, "selected": 1, "simple": 1, "yet": 1, "scalable": 1, "platform": 1, "could": 2, "power": 1, "rapidly": 1, "businesswith": 1, "able": 1, "consolidate": 1, "automate": 1, "key": 2, "financial": 1, "workflow": 1, "radically": 1, "improve": 1, "catalyst": 1, "pivotal": 1, "transformation": 1, "journeyfor": 1, "many": 1, "center": 1, "founder": 1, "cto": 1, "larry": 1, "ellison": 1, "noted": 1, "q": 1, "earnings": 1, "call": 1, "held": 1, "september": 1, "product": 2, "strategic": 1, "success": 1, "saas": 3, "layer": 1, "cloudsaas": 1, "agility": 2, "office": 3, "depotbusiness": 1, "supply": 3, "chain": 1, "depot": 3, "another": 1, "longtime": 1, "order": 1, "greater": 2, "speaking": 1, "panel": 1, "discussion": 1, "openworld": 1, "october": 1, "damon": 1, "venger": 1, "sr": 1, "inc": 1, "observed": 1, "going": 1, "helped": 1, "accelerate": 1, "progress": 1, "goaloffice": 1, "started": 1, "path": 1, "ten": 1, "ago": 1, "traditional": 1, "premise": 1, "evolved": 1, "become": 2, "leading": 1, "omnichannel": 1, "provider": 1, "service": 1, "technology": 3, "solution": 1, "looking": 1, "complexity": 1, "shift": 1, "conversation": 1, "led": 1, "cloudwere": 1, "live": 1, "several": 1, "transportation": 1, "management": 1, "epm": 1, "continuing": 1, "roll": 1, "across": 1, "changed": 1, "flexibility": 1, "speed": 1, "step": 1, "new": 2, "really": 1, "businessthe": 1, "common": 1, "theme": 1, "among": 1, "efficiency": 1, "agile": 1, "meet": 1, "today": 1, "environment": 1, "help": 1, "finding": 1, "answer": 1, "particularly": 1, "continues": 1, "embedding": 1, "emerging": 1, "artificial": 1, "intelligence": 1, "blockchain": 1, "scm": 1, "offeringsimage": 1, "credit": 1, "silhouette": 1, "man": 1, "successful": 1, "summit": 1, "climb": 1, "blue": 1, "sky": 1, "crazymedia": 1, "shutterstockread": 1, "financials": 1, "chainhcm": 1, "future": 1, "workoraclepartner": 1, "zone": 1}