{"mailonline": 1, "meet": 1, "yahooby": 1, "time": 1, "next": 1, "week": 2, "bid": 4, "fancy": 1, "taking": 1, "yahoo": 20, "list": 1, "runner": 2, "rider": 1, "expanding": 2, "th": 1, "april": 1, "deadline": 1, "loomseyebrows": 1, "raised": 1, "uk": 1, "side": 1, "atlantic": 1, "confirmed": 1, "publisher": 1, "right": 1, "wing": 1, "newspaper": 1, "daily": 3, "mail": 5, "general": 2, "trust": 1, "dmgt": 7, "contender": 2, "eye": 1, "u": 6, "profile": 1, "advertising": 2, "opportunity": 2, "online": 3, "internet": 1, "operationthe": 1, "version": 1, "launched": 1, "back": 2, "million": 3, "monthly": 1, "unique": 1, "visitor": 1, "reach": 1, "far": 1, "outstrips": 1, "would": 13, "enable": 1, "scale": 2, "presence": 1, "significantly": 1, "february": 1, "third": 1, "visited": 1, "platform": 1, "attracting": 1, "people": 1, "according": 1, "research": 1, "firm": 3, "comscorethe": 1, "publishing": 1, "group": 3, "ambition": 1, "plain": 1, "see": 2, "bought": 2, "elite": 1, "millennialfocused": 1, "website": 1, "last": 3, "year": 3, "reported": 1, "also": 2, "formed": 1, "partnership": 2, "american": 1, "personality": 1, "dr": 1, "phil": 1, "mcgraw": 1, "create": 2, "dailymailtv": 1, "showscuttlebutt": 1, "suggests": 1, "two": 1, "possible": 1, "way": 1, "approach": 3, "first": 3, "acquire": 2, "medium": 2, "asset": 4, "eg": 1, "news": 2, "finance": 1, "video": 2, "arm": 1, "katie": 1, "couric": 1, "etc": 1, "private": 4, "equity": 4, "took": 1, "ownership": 1, "full": 1, "companythe": 1, "option": 1, "appears": 1, "table": 1, "spinoff": 1, "new": 1, "company": 1, "majority": 1, "shareholder": 1, "merging": 2, "onlinerival": 1, "bidswhatever": 1, "taken": 1, "face": 2, "stiff": 1, "competition": 1, "microsoft": 4, "interest": 1, "making": 2, "form": 1, "probably": 1, "order": 1, "secure": 1, "existing": 1, "search": 2, "deal": 3, "currently": 1, "result": 2, "around": 2, "traffic": 1, "delivered": 1, "via": 1, "microsofts": 1, "bingdespite": 1, "believed": 2, "wont": 1, "participate": 1, "bidding": 4, "round": 2, "bitten": 1, "twice": 1, "offered": 2, "billion": 2, "take": 1, "premium": 1, "latter": 1, "promptly": 1, "rejected": 2, "three": 1, "month": 1, "later": 1, "price": 1, "today": 1, "worth": 1, "billionin": 1, "universe": 1, "whatmighthavebeens": 1, "merger": 1, "gone": 1, "potentially": 1, "left": 1, "better": 1, "placed": 1, "compete": 1, "rise": 1, "google": 2, "part": 2, "kept": 1, "powder": 1, "dry": 1, "prospect": 1, "althought": 1, "widely": 1, "play": 1, "although": 1, "antitrust": 1, "attention": 1, "attract": 1, "might": 1, "well": 1, "enough": 1, "deter": 1, "itbut": 1, "front": 1, "remains": 1, "verizon": 7, "aol": 4, "present": 1, "rapidly": 1, "mobile": 3, "space": 1, "programmatic": 1, "ad": 1, "business": 2, "could": 2, "combine": 1, "build": 1, "stronger": 1, "offering": 1, "contentthe": 1, "largest": 1, "phone": 1, "carrier": 1, "frame": 1, "since": 1, "december": 1, "publicly": 1, "stated": 1, "interested": 1, "purchasing": 1, "yahooverizon": 1, "favored": 1, "candidate": 1, "market": 1, "watcher": 1, "robert": 1, "peck": 1, "analyst": 1, "suntrust": 1, "robinson": 1, "humphrey": 1, "noteswe": 1, "continue": 1, "believe": 1, "leading": 1, "afford": 1, "pay": 1, "given": 2, "potential": 1, "cost": 2, "saving": 1, "concern": 1, "expressed": 1, "health": 1, "core": 1, "expect": 1, "robust": 1, "process": 1, "due": 2, "underlying": 1, "value": 2, "pieceswe": 1, "think": 1, "strategic": 1, "acquirer": 1, "much": 1, "higher": 1, "overlap": 1, "example": 1, "little": 1, "need": 1, "sale": 1, "force": 1, "ga": 1, "administrative": 1, "functionspeck": 1, "estimate": 1, "job": 1, "top": 1, "go": 1, "end": 2, "victorywhatever": 1, "happens": 1, "staffer": 1, "successfully": 1, "win": 1, "war": 1, "likely": 1, "road": 1, "embattled": 1, "ceo": 3, "marissa": 1, "mayer": 2, "lowell": 1, "mcadam": 1, "record": 1, "stating": 1, "tim": 1, "armstrong": 1, "good": 1, "thing": 1, "investorsfor": 1, "reportedly": 1, "working": 1, "keep": 1, "topmy": 1, "takeverizon": 1, "one": 1, "beatread": 1, "content": 1, "marketingmobilesocialuser": 1, "experience": 1}