{"diginomica": 4, "hit": 3, "oracle": 23, "openworld": 8, "blowout": 2, "analysis": 3, "customer": 13, "use": 4, "case": 9, "den": 6, "brian": 2, "paul": 4, "derek": 4, "jessicaquotage": 1, "overall": 1, "year": 4, "event": 4, "clear": 2, "happy": 2, "analyst": 1, "le": 3, "grumpy": 1, "usual": 1, "always": 1, "swagger": 1, "step": 1, "many": 4, "thing": 6, "going": 3, "imply": 1, "change": 3, "need": 3, "make": 3, "starting": 1, "take": 4, "root": 1, "bearing": 1, "fruit": 1, "denmypov": 1, "prolific": 1, "team": 1, "ground": 2, "open": 3, "world": 3, "good": 7, "turned": 1, "un": 1, "showed": 2, "cloud": 16, "data": 4, "better": 6, "experience": 3, "converging": 1, "there": 1, "typically": 1, "two": 3, "camp": 1, "come": 2, "evaluating": 1, "legacy": 2, "provider": 2, "struggling": 1, "pure": 2, "saas": 2, "player": 1, "enterprise": 7, "frontrunner": 1, "deep": 1, "pocket": 1, "aggressive": 2, "plan": 1, "dominate": 1, "never": 1, "simple": 1, "aint": 1, "itif": 1, "want": 3, "quick": 2, "hir": 1, "pas": 1, "go": 12, "jump": 1, "directly": 1, "verdict": 2, "get": 4, "grouch": 1, "end": 3, "long": 1, "trust": 1, "ended": 1, "upbeat": 1, "note": 4, "mean": 2, "got": 1, "job": 3, "done": 2, "still": 2, "raise": 1, "question": 2, "check": 3, "cloudy": 3, "management": 1, "conundrum": 1, "must": 1, "solve": 1, "address": 1, "post": 3, "safe": 1, "harbor": 1, "limbo": 1, "missing": 2, "piece": 4, "developer": 1, "secure": 1, "style": 3, "tackle": 1, "one": 7, "key": 4, "announcementsdebates": 1, "conference": 1, "chipfancy": 1, "another": 2, "angle": 2, "keynote": 2, "brians": 3, "omnicloud": 2, "relevance": 1, "today": 2, "digital": 3, "omnievent": 1, "blogger": 1, "coin": 1, "new": 3, "omniterm": 1, "ugh": 1, "thats": 3, "way": 4, "framing": 1, "privatepublic": 1, "option": 1, "give": 3, "sold": 1, "strategy": 1, "sound": 2, "like": 4, "he": 1, "fence": 1, "choice": 2, "operating": 1, "cost": 2, "side": 1, "maintain": 1, "stay": 1, "tunedtheres": 1, "look": 6, "future": 2, "guest": 1, "contributor": 1, "wallbank": 1, "catz": 3, "say": 5, "unrecognisable": 1, "five": 1, "share": 2, "frank": 2, "view": 3, "past": 1, "ahead": 1, "coceo": 1, "safra": 2, "offering": 1, "takefor": 1, "transformation": 1, "shift": 1, "repelling": 1, "twin": 1, "threat": 1, "aws": 1, "microsoft": 1, "azure": 1, "infrastructure": 1, "also": 5, "attempting": 1, "muscle": 1, "apps": 2, "competitor": 1, "define": 2, "company": 4, "challenge": 1, "probably": 2, "great": 1, "tech": 6, "wreck": 1, "see": 6, "coverage": 1, "u": 4, "ontooracle": 1, "galoreoracle": 1, "ebay": 1, "run": 1, "scrappy": 1, "knowledge": 1, "experiment": 1, "yield": 1, "result": 3, "shorter": 1, "project": 2, "usually": 3, "contact": 1, "center": 1, "experiencegeneral": 1, "motor": 1, "crisis": 1, "moment": 1, "helped": 1, "drive": 1, "social": 1, "cx": 1, "business": 3, "adversity": 1, "improved": 2, "relationshipsmacys": 1, "praise": 1, "changed": 1, "behaviour": 1, "warns": 1, "old": 3, "rare": 1, "hear": 3, "giving": 1, "vendor": 4, "kudos": 1, "behavior": 1, "stage": 1, "sidesmilestones": 1, "american": 1, "airline": 2, "passenger": 2, "journey": 1, "jessica": 2, "verge": 1, "air": 1, "merger": 1, "learn": 2, "whats": 1, "store": 1, "aa": 1, "try": 2, "merge": 1, "system": 1, "improve": 1, "least": 1, "high": 2, "value": 1, "type": 1, "admiral": 1, "club": 1, "access": 1, "ahemkenya": 1, "airway": 2, "silo": 1, "hub": 1, "lead": 2, "fragmented": 1, "last": 2, "here": 1, "kenya": 1, "itvendor": 1, "hogged": 1, "headline": 2, "ibm": 10, "ahad": 1, "major": 1, "analytics": 5, "week": 5, "expected": 3, "spark": 5, "grabbed": 1, "bandwidth": 1, "stuart": 2, "story": 5, "insight": 4, "putting": 1, "analyticselsewhere": 1, "vendorland": 1, "phil": 1, "workforce": 2, "workday": 4, "product": 1, "leighanne": 1, "levensaler": 1, "hr": 3, "help": 1, "manager": 1, "leader": 1, "riffed": 1, "big": 3, "ol": 2, "salesforce": 4, "ecosystem": 1, "projection": 1, "million": 2, "billion": 1, "gdp": 1, "impact": 1, "bold": 1, "claim": 1, "sense": 1, "timing": 1, "outright": 1, "bashing": 1, "definitely": 1, "bit": 1, "judo": 1, "hereand": 1, "oncebig": 1, "became": 1, "footnote": 1, "adp": 2, "v": 3, "zenefits": 1, "dismissed": 1, "prejudice": 1, "time": 5, "although": 1, "striking": 1, "day": 1, "release": 1, "global": 1, "benefit": 2, "solution": 2, "peril": 1, "cooptition": 1, "eh": 1, "oh": 1, "buff": 1, "appreciate": 1, "highlight": 1, "technology": 2, "la": 1, "vegasjons": 1, "grab": 1, "bag": 1, "enjoyed": 1, "chris": 2, "middleton": 1, "f": 1, "state": 1, "music": 2, "industry": 4, "pandora": 2, "box": 1, "positive": 2, "strike": 1, "wrong": 5, "score": 1, "quote": 1, "unless": 1, "someone": 1, "explain": 1, "provides": 1, "content": 1, "streaming": 1, "service": 3, "monetize": 1, "advertising": 1, "musician": 1, "money": 1, "standing": 1, "rain": 1, "hour": 1, "acoustic": 1, "guitar": 1, "online": 2, "literally": 1, "hundred": 1, "thousand": 1, "play": 3, "month": 1, "yup": 1, "blammoalso": 1, "dug": 1, "phils": 1, "prezi": 3, "mission": 1, "wean": 1, "people": 1, "powerpoint": 2, "ford": 1, "focus": 2, "software": 3, "tesla": 1, "yeah": 2, "bux": 1, "analogy": 1, "hold": 1, "finally": 1, "martin": 2, "dump": 1, "cold": 1, "water": 1, "skill": 3, "hype": 2, "cynical": 1, "pour": 1, "culture": 1, "closed": 1, "idea": 1, "whole": 1, "bottom": 1, "yupbest": 1, "rest": 1, "double": 2, "watson": 7, "doug": 2, "henschen": 2, "stephen": 2, "ogradyquotage": 1, "ibms": 3, "intuitive": 1, "cloudbased": 1, "app": 1, "naturallanguage": 1, "questionandanswer": 1, "capability": 1, "smart": 1, "automated": 1, "recommendation": 1, "visualization": 1, "cognos": 1, "well": 6, "aging": 1, "intelligence": 3, "suite": 1, "born": 1, "earlier": 1, "era": 1, "announced": 1, "significant": 1, "facelift": 1, "henschenmypov": 1, "notable": 1, "validation": 2, "general": 1, "needed": 1, "much": 1, "spotlight": 1, "upgrade": 1, "wade": 1, "boatload": 1, "announcement": 1, "offer": 1, "im": 2, "particularly": 1, "intrigued": 1, "promoting": 1, "citizen": 1, "scientiststhe": 1, "intriguing": 1, "precisely": 1, "nobody": 1, "else": 1, "ogrady": 2, "point": 4, "crossing": 1, "amazon": 1, "age": 1, "disruption": 1, "proven": 1, "beastly": 1, "difficult": 1, "commercialize": 1, "turnaround": 1, "ensw": 2, "narrative": 1, "find": 1, "interesting": 1, "disrupted": 1, "across": 1, "market": 1, "responding": 1, "kind": 1, "via": 1, "internal": 1, "innovation": 1, "source": 1, "acquisition": 1, "common": 1, "thread": 1, "bye": 2, "commodity": 1, "valueadd": 1, "stickother": 1, "standoutsartificial": 1, "human": 4, "artificial": 1, "know": 3, "mary": 1, "branscombe": 1, "reframes": 1, "ai": 3, "debate": 1, "away": 1, "robotbad": 1, "robot": 1, "practical": 1, "often": 1, "designer": 1, "culprit": 1, "bias": 1, "embedded": 1, "algorithm": 2, "machine": 1, "learning": 1, "relieas": 1, "upon": 1, "example": 1, "cmu": 1, "study": 2, "found": 1, "ad": 1, "targeting": 1, "paying": 1, "men": 1, "woman": 2, "related": 1, "wireds": 1, "humane": 1, "understand": 1, "asks": 1, "build": 1, "empathy": 1, "machineswomen": 1, "technologist": 1, "tell": 1, "succeed": 1, "diversity": 2, "inclusion": 1, "reader": 2, "liked": 2, "nice": 1, "profiled": 1, "career": 1, "development": 1, "tip": 1, "leading": 1, "especially": 3, "went": 1, "beyond": 2, "gender": 1, "thoughtexperience": 1, "downside": 1, "recent": 3, "survey": 1, "indicates": 1, "number": 6, "young": 1, "female": 2, "moving": 2, "increasing": 1, "issue": 4, "twentyman": 1, "talent": 1, "pipeline": 1, "problemoracle": 1, "rimini": 1, "street": 2, "clarifies": 2, "rule": 1, "thirdparty": 1, "maintenance": 3, "youre": 1, "following": 1, "closely": 1, "might": 3, "think": 2, "ruling": 2, "favor": 1, "setback": 1, "third": 2, "party": 2, "scavo": 3, "around": 1, "gut": 1, "doesnt": 1, "awarded": 1, "far": 1, "put": 2, "legality": 1, "longer": 1, "game": 1, "hopefully": 1, "win": 1, "along": 1, "lawyershonorable": 1, "mentionsituational": 1, "awareness": 1, "sale": 2, "success": 3, "process": 1, "buy": 1, "bingomicrosofts": 1, "agile": 4, "scale": 2, "dont": 3, "fanboysgals": 1, "dandy": 1, "isnt": 4, "article": 6, "blame": 1, "forbes": 1, "multipage": 1, "clunk": 1, "thatevent": 1, "report": 3, "top": 2, "takeaway": 1, "concern": 1, "didnt": 2, "enough": 1, "yetsurviving": 1, "eye": 1, "storm": 1, "delightfully": 1, "curmodgeonly": 1, "curmodgeons": 1, "back": 2, "blogstomping": 1, "groundsoutsourcing": 1, "life": 1, "support": 1, "failing": 1, "invest": 1, "asaservice": 1, "stake": 1, "groundescaping": 1, "superstar": 1, "syndrome": 1, "different": 1, "work": 1, "eruditeannoyingbrilliant": 1, "series": 1, "weve": 1, "topictake": 1, "si": 1, "land": 1, "cant": 2, "second": 3, "early": 1, "return": 1, "yesframework": 1, "discussion": 1, "computing": 1, "page": 1, "shame": 1, "cap": 1, "fruitful": 1, "serieswhy": 1, "spending": 1, "cracked": 1, "let": 3, "grim": 1, "shall": 1, "wesidenote": 1, "strongest": 1, "collection": 1, "honorable": 1, "mention": 1, "history": 1, "column": 1, "folkswhiffsso": 1, "orwell": 2, "estate": 3, "copyright": 3, "enforcer": 1, "sends": 2, "takedown": 2, "link": 2, "torrentfreak": 1, "cmon": 1, "hope": 2, "prince": 1, "hostile": 1, "using": 1, "tweet": 1, "saidorwell": 1, "httpstcokeflcjrfo": 1, "truth": 1, "stranger": 1, "sadder": 1, "fiction": 1, "jon": 1, "reed": 1, "jonerp": 1, "october": 2, "buddy": 1, "gregnotso": 1, "replied": 1, "yet": 1, "right": 2, "york": 1, "jumping": 1, "virtual": 2, "reality": 2, "sending": 1, "google": 1, "cardboard": 1, "kit": 1, "anticipation": 1, "upcoming": 1, "film": 1, "nov": 1, "ordinarily": 1, "id": 3, "could": 2, "ill": 1, "ask": 1, "reverse": 1, "rightim": 1, "loath": 1, "whack": 1, "david": 1, "linthicum": 7, "blog": 2, "frame": 1, "couple": 1, "ago": 1, "published": 2, "real": 1, "cow": 1, "fart": 1, "writing": 1, "wall": 2, "critique": 1, "sap": 8, "extent": 1, "guard": 1, "fatalistic": 1, "absurdity": 1, "missed": 1, "obvious": 1, "sign": 2, "acted": 1, "smartly": 1, "saved": 1, "miss": 5, "saving": 1, "seems": 1, "shoveling": 1, "dirt": 1, "financial": 1, "grave": 1, "chock": 1, "full": 1, "act": 1, "chanceswith": 1, "closer": 1, "sad": 2, "framed": 1, "recently": 1, "reported": 1, "news": 1, "problem": 1, "earnings": 2, "april": 1, "fact": 1, "q": 1, "parsed": 1, "revenue": 1, "subject": 1, "linthicums": 1, "growing": 1, "impressive": 1, "millionnow": 1, "argument": 1, "looong": 1, "true": 1, "proclaims": 1, "criticize": 1, "public": 1, "part": 1, "shana": 1, "immature": 1, "articulated": 1, "calling": 1, "cloudearnings": 1, "situation": 1, "laying": 1, "little": 1, "thick": 1, "almost": 1, "half": 1, "executing": 1, "rewarding": 1, "necessarily": 1, "dictate": 1, "failure": 2, "anotherupdated": 1, "text": 1, "research": 1, "baffling": 1, "happened": 2, "publish": 1, "doubt": 1, "assume": 1, "older": 1, "somehow": 1, "given": 1, "fresh": 3, "oct": 1, "date": 1, "without": 2, "revision": 1, "appeared": 1, "r": 1, "best": 2, "scenario": 2, "sloppy": 1, "infoworld": 1, "updatefix": 1, "since": 1, "th": 1, "wont": 1, "comment": 1, "worst": 1, "journalistic": 1, "credibility": 1, "addressedhits": 1, "mulligan": 1, "next": 1, "update": 1, "pstwhich": 1, "merit": 1, "commentsmost": 1, "selected": 1, "curated": 1, "jonerpnewsfeed": 1, "mypov": 1, "borrowed": 1, "reluctant": 1, "permission": 1, "ubiquitous": 1, "ray": 1, "wangimage": 1, "credit": 1, "cheerful": 1, "chubby": 1, "man": 1, "ra": 1, "studio": 1, "child": 1, "anna": 1, "omelchenko": 1, "waiter": 1, "suggesting": 1, "bottle": 1, "minerva": 1, "studiom": 1, "overworked": 1, "businessman": 2, "bloomua": 1, "choosing": 1, "road": 1, "creativa": 1, "fotoliacomdisclosure": 1, "infosys": 1, "premier": 1, "partner": 1, "writingread": 1, "archiveshits": 1}