{"weekend": 1, "watched": 1, "diversity": 8, "debacle": 1, "google": 5, "unfold": 1, "pretty": 1, "good": 1, "news": 1, "hold": 2, "lesson": 1, "everyone": 1, "part": 3, "technology": 1, "industrywhat": 1, "happened": 1, "googlelast": 1, "friday": 1, "engineer": 5, "circulated": 1, "internal": 4, "memo": 8, "entitledgoogles": 1, "ideological": 2, "echo": 1, "chamberit": 1, "didnt": 1, "take": 6, "long": 2, "go": 2, "viral": 1, "inside": 1, "interwebs": 1, "via": 1, "selected": 1, "tweet": 1, "techmeme": 1, "many": 5, "thread": 1, "topicwe": 1, "know": 3, "motivation": 1, "behind": 1, "face": 1, "dont": 4, "find": 1, "totality": 1, "especially": 1, "offensive": 1, "although": 1, "plenty": 2, "saw": 1, "blatantly": 1, "sexist": 2, "passage": 2, "particular": 2, "caught": 1, "attentionnote": 1, "im": 4, "saying": 1, "men": 4, "differ": 2, "woman": 4, "following": 1, "way": 2, "difference": 3, "simply": 1, "stating": 1, "distribution": 1, "preference": 1, "ability": 2, "due": 1, "biological": 1, "cause": 1, "may": 1, "explain": 1, "see": 3, "equal": 1, "representation": 1, "tech": 1, "leadership": 1, "small": 1, "there": 1, "significant": 1, "overlap": 1, "cant": 1, "say": 1, "anything": 1, "individual": 3, "given": 1, "population": 1, "level": 1, "distributionsof": 1, "nothing": 1, "particularly": 2, "controversial": 1, "statement": 2, "naturenurture": 1, "debate": 5, "continue": 3, "day": 2, "however": 2, "writer": 1, "went": 1, "list": 1, "whole": 2, "set": 1, "unsupported": 2, "reason": 2, "underpin": 1, "idea": 1, "certainly": 1, "raised": 1, "temperature": 1, "arguing": 1, "little": 4, "understanding": 1, "create": 1, "productive": 1, "development": 1, "team": 2, "matterive": 1, "heard": 1, "several": 1, "call": 1, "increased": 1, "empathy": 1, "issue": 6, "strongly": 1, "support": 4, "trying": 1, "understand": 2, "people": 1, "think": 2, "relying": 1, "affective": 1, "empathyfeeling": 1, "anothers": 1, "paincauses": 1, "u": 4, "focus": 2, "anecdote": 1, "favor": 1, "similar": 1, "harbor": 1, "irrational": 1, "dangerous": 1, "bias": 4, "emotionally": 2, "unengaged": 1, "help": 1, "better": 3, "factsgizmodo": 1, "full": 1, "screedthe": 1, "public": 5, "medium": 2, "responsethe": 1, "response": 2, "ugly": 1, "kara": 1, "swisher": 2, "recodeexpressed": 1, "general": 1, "tenor": 1, "sharply": 1, "critical": 2, "memoit": 1, "contains": 1, "series": 1, "describe": 1, "twaddle": 1, "wrapped": 1, "undeserved": 1, "protection": 1, "free": 1, "speech": 1, "hey": 1, "bros": 1, "agree": 1, "thats": 1, "opinion": 2, "youll": 1, "first": 2, "amendment": 1, "allms": 1, "shrinking": 1, "violet": 1, "topic": 9, "sure": 1, "phrasing": 1, "terribly": 1, "helpfuli": 1, "prefer": 1, "view": 6, "partially": 1, "illinformed": 1, "basic": 1, "principle": 2, "collaboration": 1, "author": 3, "attempt": 1, "draw": 1, "attention": 1, "avail": 1, "since": 2, "concentration": 1, "claimed": 1, "antidiversity": 1, "elementsgoogle": 1, "swat": 1, "backdanielle": 1, "brown": 3, "newly": 1, "minted": 1, "officer": 1, "impossible": 1, "position": 3, "new": 1, "job": 1, "faced": 1, "existential": 1, "crisis": 1, "paused": 1, "making": 2, "clear": 1, "expressed": 2, "shared": 2, "googlemany": 1, "read": 1, "document": 2, "someone": 2, "engineering": 1, "organization": 3, "expressing": 1, "natural": 1, "characteristic": 1, "different": 1, "gender": 4, "well": 3, "whether": 1, "one": 3, "speak": 1, "freely": 1, "thing": 2, "like": 3, "found": 1, "advanced": 1, "incorrect": 1, "assumption": 2, "going": 1, "link": 1, "viewpoint": 1, "company": 2, "endorses": 1, "promotes": 1, "encouragesdiversity": 1, "inclusion": 2, "fundamental": 2, "value": 1, "culture": 2, "cultivate": 1, "unequivocal": 1, "belief": 2, "success": 1, "stand": 1, "committed": 1, "haul": 1, "ari": 1, "balogh": 1, "said": 2, "g": 1, "post": 1, "building": 1, "open": 1, "inclusive": 1, "environment": 1, "core": 1, "right": 1, "nuff": 1, "unpopular": 1, "viewin": 1, "reportssuggest": 1, "point": 4, "struck": 1, "thismotherboard": 1, "spoke": 1, "current": 1, "employee": 2, "agrees": 1, "wrote": 1, "manifesto": 1, "left": 1, "created": 1, "politically": 2, "correct": 1, "monoculture": 1, "maintains": 1, "shaming": 1, "dissenter": 1, "silencethe": 1, "fact": 3, "colleague": 1, "calling": 1, "firedon": 1, "forumsproves": 1, "silo": 1, "dissenting": 1, "want": 1, "silenced": 1, "second": 1, "told": 1, "motherboard": 1, "argument": 2, "easier": 1, "virtue": 1, "signal": 1, "mentioning": 1, "social": 3, "network": 1, "angry": 1, "offended": 1, "discussion": 1, "timewhere": 1, "hereit": 1, "difficult": 1, "heregrappling": 1, "problematic": 1, "considerable": 2, "nuance": 1, "element": 1, "situationally": 1, "contextual": 1, "flavored": 1, "time": 3, "product": 1, "system": 1, "tough": 1, "nut": 1, "crack": 1, "bound": 1, "combination": 1, "superstition": 1, "more": 1, "unconscious": 1, "biaswhen": 1, "studied": 1, "science": 1, "section": 1, "teaching": 1, "form": 1, "essentially": 1, "study": 1, "income": 2, "wealth": 2, "inequality": 5, "order": 1, "make": 1, "subject": 1, "digestible": 1, "broken": 1, "race": 2, "sex": 1, "age": 2, "come": 1, "back": 3, "outcome": 1, "deliberately": 1, "biased": 1, "critique": 1, "white": 1, "middle": 1, "class": 1, "even": 1, "justification": 1, "characterization": 1, "neither": 1, "exclusive": 1, "universalthe": 1, "today": 1, "often": 1, "charged": 1, "term": 1, "tell": 1, "progress": 1, "made": 2, "year": 1, "started": 1, "studying": 1, "topicfor": 1, "example": 1, "m": 2, "act": 1, "shut": 2, "original": 2, "story": 2, "sense": 2, "sympathy": 1, "talk": 1, "silence": 1, "equally": 2, "need": 2, "deprive": 1, "otherwise": 2, "incendiary": 1, "oxygenthe": 1, "shocking": 1, "error": 2, "failed": 1, "research": 1, "unquestionably": 1, "worth": 1, "correction": 1, "blanket": 1, "negate": 1, "entire": 2, "wrong": 1, "headed": 1, "swathe": 1, "scientific": 1, "societal": 1, "advance": 1, "would": 2, "swept": 1, "asideat": 1, "least": 1, "believe": 1, "step": 1, "try": 1, "figure": 1, "meaning": 1, "person": 1, "attempting": 1, "communicate": 1, "finding": 1, "merit": 1, "along": 1, "waymy": 1, "reading": 1, "suggests": 1, "frustration": 1, "transparency": 1, "conflict": 1, "length": 1, "breadth": 1, "also": 1, "suggest": 1, "spent": 1, "thinking": 1, "attempted": 1, "square": 1, "competing": 1, "including": 1, "thorny": 1, "problem": 1, "group": 1, "confirmation": 1, "marking": 1, "academic": 1, "paper": 1, "get": 1, "cc": 1, "definitely": 1, "grade": 1, "studentregular": 1, "reader": 1, "diginomica": 1, "strong": 1, "threatened": 1, "lgbt": 1, "le": 1, "vocal": 1, "silent": 2, "round": 1, "almost": 1, "around": 1, "every": 1, "far": 1, "perfect": 1, "disagree": 1, "behave": 1, "rabbleso": 1, "become": 1, "mot": 1, "du": 1, "jour": 1, "quickly": 1, "fizzle": 1, "next": 1, "blow": 1, "opportunity": 1, "improvement": 1, "credibly": 1, "reported": 1, "domainwe": 1, "deserve": 1, "nature": 1, "work": 2, "rapidly": 1, "changing": 1, "positive": 1, "antidote": 1, "taking": 1, "center": 1, "stageimage": 1, "credit": 1, "image": 1, "sourcesread": 1, "diversityfuture": 1, "workhcm": 1, "digital": 1, "future": 1}