{"piece": 1, "vinnie": 1, "mirchandanis": 1, "assessment": 1, "oracle": 3, "v": 1, "rimini": 1, "street": 1, "tipped": 1, "edge": 1, "writing": 1, "something": 1, "thats": 1, "mind": 1, "last": 2, "week": 1, "saas": 6, "price": 8, "hike": 3, "saysthe": 1, "day": 1, "attended": 1, "court": 1, "jarring": 1, "hear": 1, "attorney": 1, "talk": 1, "contract": 4, "term": 3, "practice": 1, "two": 1, "decade": 1, "ago": 1, "marketing": 1, "associated": 1, "today": 2, "language": 1, "multitenancy": 1, "availability": 1, "zone": 1, "global": 1, "deliveryyeah": 1, "pointsrecently": 1, "ive": 2, "heard": 1, "rumbling": 1, "among": 2, "buyer": 2, "anywhere": 1, "percent": 1, "demanded": 1, "different": 1, "vendor": 7, "way": 3, "limited": 1, "big": 1, "boy": 1, "client": 1, "control": 1, "large": 1, "clout": 1, "market": 1, "placein": 1, "one": 2, "case": 4, "person": 3, "speaking": 1, "admitted": 1, "severe": 1, "remorse": 1, "happened": 1, "matter": 1, "operational": 1, "economics": 1, "well": 1, "understood": 1, "right": 2, "wrongin": 1, "particular": 1, "concerned": 1, "previously": 1, "contacted": 1, "summer": 1, "year": 2, "saying": 1, "company": 4, "make": 2, "quick": 1, "decision": 3, "time": 2, "salesperson": 1, "near": 1, "chosen": 1, "solution": 1, "yelling": 1, "phone": 1, "simply": 1, "deali": 1, "unhappy": 1, "circumstance": 1, "described": 1, "said": 1, "best": 1, "thing": 3, "pause": 1, "work": 1, "various": 1, "issue": 2, "unfortunately": 1, "backed": 1, "corner": 1, "convinced": 1, "get": 1, "deal": 1, "sort": 1, "done": 1, "could": 3, "replace": 1, "worn": 1, "system": 1, "point": 5, "seriously": 1, "questioned": 1, "going": 2, "month": 1, "either": 1, "almost": 1, "never": 1, "much": 5, "difference": 1, "catastrophici": 1, "also": 1, "experience": 1, "choice": 2, "aware": 1, "ofthe": 1, "tactic": 1, "employed": 1, "pressure": 1, "potential": 1, "customer": 3, "making": 2, "good": 3, "sale": 1, "people": 1, "guilt": 1, "tripper": 1, "contrary": 1, "advice": 1, "capitulated": 1, "say": 1, "lucka": 1, "bit": 1, "come": 3, "view": 1, "err": 1, "weve": 1, "hit": 1, "difficult": 1, "apart": 1, "anything": 2, "else": 1, "seen": 1, "exact": 1, "wording": 2, "final": 1, "would": 1, "checked": 2, "around": 1, "annual": 1, "increasesall": 1, "want": 1, "increase": 3, "whether": 1, "justified": 1, "industry": 1, "inflation": 1, "taking": 1, "ride": 1, "data": 1, "center": 1, "cost": 4, "falling": 2, "compute": 1, "little": 3, "justification": 1, "percentage": 2, "argue": 2, "labor": 2, "always": 1, "back": 1, "arbitrage": 1, "especially": 2, "software": 1, "component": 1, "largely": 1, "breakfix": 1, "maintenance": 1, "alternative": 1, "track": 1, "rd": 1, "revenue": 1, "argument": 1, "number": 1, "usuallythe": 1, "clue": 1, "respond": 1, "gave": 1, "pointer": 1, "suspect": 1, "may": 1, "caught": 1, "onerous": 1, "standard": 1, "form": 1, "otherwise": 1, "negotiated": 1, "whats": 2, "nextmy": 1, "guess": 1, "rock": 1, "hard": 1, "place": 1, "room": 1, "maneuver": 1, "likely": 1, "possible": 1, "shave": 1, "depending": 1, "upon": 1, "use": 1, "possibly": 2, "retire": 1, "shelf": 1, "ware": 1, "although": 1, "hold": 1, "hope": 1, "even": 1, "lesson": 1, "clearnever": 1, "pressured": 1, "wrong": 1, "decisionnever": 1, "let": 1, "push": 1, "corneralways": 1, "understand": 1, "long": 1, "implication": 1, "youre": 1, "signing": 1, "multiyear": 1, "dealslook": 1, "clause": 1, "give": 1, "related": 1, "storage": 1, "event": 1, "based": 1, "overagesin": 1, "technology": 1, "old": 1, "saw": 1, "marry": 1, "haste": 1, "repent": 1, "leisure": 1, "true": 1, "ever": 1, "dont": 1, "sleep": 1, "walk": 1, "shotgun": 1, "wedding": 1, "eitheryou": 1, "warnedas": 1, "side": 1, "note": 1, "pleased": 1, "learn": 1, "part": 1, "ibm": 1, "page": 2, "replaced": 1, "four": 1, "simpler": 1, "clearer": 1, "everyoneread": 1, "cloud": 1, "platform": 1, "infrastructure": 1, "architecture": 1}