{"youre": 1, "couple": 1, "ambitious": 1, "young": 1, "entrepreneur": 1, "hoping": 1, "kickstart": 1, "new": 2, "trend": 1, "disused": 1, "shipping": 1, "container": 1, "converted": 1, "shop": 2, "boxpark": 2, "popup": 2, "mall": 1, "london": 1, "shoreditch": 1, "district": 1, "suitably": 1, "hipsterish": 1, "place": 1, "startat": 1, "unit": 1, "site": 2, "daniela": 1, "pillhofer": 2, "peter": 1, "honegger": 2, "newcomer": 4, "wine": 12, "mission": 1, "make": 1, "austrian": 4, "fashionable": 1, "younger": 2, "crowdits": 1, "interesting": 2, "idea": 2, "older": 1, "drinker": 1, "may": 2, "still": 2, "remember": 1, "industry": 2, "antifreeze": 1, "scandal": 2, "mids": 1, "revealed": 1, "tainted": 1, "diethylene": 1, "glycol": 1, "otherwise": 1, "known": 1, "engine": 1, "coolant": 1, "one": 1, "biggest": 1, "food": 1, "drink": 1, "last": 1, "century": 1, "collapsed": 1, "million": 1, "bottle": 2, "withdrawn": 1, "shelvesbut": 1, "aficianados": 1, "thats": 3, "ancient": 1, "history": 1, "fact": 1, "either": 1, "even": 2, "born": 1, "thirty": 1, "year": 3, "import": 1, "rise": 1, "according": 2, "figure": 2, "statistik": 1, "austria": 1, "despite": 1, "four": 1, "harvest": 1, "shortfall": 1, "past": 1, "five": 1, "export": 1, "quantity": 1, "valueonline": 1, "measuresnewcomer": 1, "cofounder": 2, "determined": 1, "profit": 1, "resurgence": 1, "interest": 1, "via": 2, "retail": 6, "outlet": 2, "ecommerce": 1, "wholesale": 1, "business": 3, "currently": 1, "sell": 2, "around": 3, "restaurant": 1, "mostly": 1, "londonbut": 1, "opening": 1, "physical": 1, "raise": 1, "paymenthandling": 1, "issue": 2, "small": 2, "independent": 1, "trader": 1, "every": 1, "day": 1, "many": 1, "forced": 1, "turn": 2, "customer": 6, "away": 1, "cost": 2, "complexity": 1, "signing": 1, "traditional": 3, "card": 10, "payment": 8, "service": 3, "mean": 1, "decide": 1, "accept": 2, "cash": 4, "king": 1, "said": 1, "much": 3, "prefer": 1, "pay": 2, "credit": 1, "debit": 1, "say": 2, "pillhoferfrom": 1, "start": 1, "knew": 1, "able": 1, "without": 2, "going": 1, "really": 3, "important": 1, "u": 3, "particularly": 1, "product": 2, "people": 1, "dont": 1, "carry": 1, "daysand": 1, "right": 1, "want": 1, "cardin": 1, "order": 1, "handle": 1, "us": 2, "izettle": 8, "along": 1, "competitor": 1, "payleven": 1, "sumup": 1, "mobile": 1, "technology": 1, "deliver": 1, "lowcost": 1, "alternative": 1, "servicesit": 1, "work": 1, "like": 1, "reader": 3, "connects": 1, "directly": 2, "bluetooth": 1, "ipad": 1, "iphone": 1, "owned": 1, "app": 4, "downloaded": 2, "onto": 1, "device": 1, "providing": 1, "staff": 1, "entire": 1, "pointofsale": 2, "environment": 1, "process": 1, "store": 1, "paymenta": 1, "receipt": 1, "meanwhile": 2, "emailed": 1, "printed": 1, "nearby": 1, "printer": 1, "word": 1, "smallbusiness": 1, "owner": 1, "tablet": 2, "smartphone": 1, "becomes": 1, "terminal": 1, "electronic": 1, "point": 2, "sale": 2, "epos": 1, "management": 1, "software": 1, "package": 1, "combinedcheersthe": 1, "barrier": 1, "entry": 1, "lower": 1, "associated": 1, "costly": 1, "set": 1, "come": 1, "longterm": 1, "contract": 1, "involving": 1, "high": 1, "monthly": 3, "fee": 2, "contrast": 1, "bought": 1, "outright": 1, "free": 1, "involved": 1, "instead": 2, "retailer": 1, "charged": 1, "pertransaction": 1, "basis": 1, "starting": 1, "per": 1, "transaction": 3, "dropping": 1, "total": 1, "value": 1, "salesin": 1, "first": 1, "made": 1, "life": 1, "good": 1, "deal": 1, "easier": 1, "team": 1, "honeggerwe": 1, "liked": 1, "making": 1, "system": 1, "easy": 1, "use": 1, "possible": 1, "scan": 1, "picture": 2, "display": 1, "click": 1, "quickly": 1, "add": 1, "easeofuse": 1, "main": 1, "selling": 1, "ustoday": 1, "run": 1, "manually": 1, "entered": 1, "give": 1, "full": 1, "hold": 1, "event": 1, "venue": 1, "quite": 1, "frequently": 1, "flexible": 1, "accepting": 1, "take": 2, "lot": 1, "equipment": 1, "storewe": 1, "plug": 1, "smartphones": 1, "instore": 1, "basically": 1, "anywhere": 1, "everywhere": 1, "convenient": 1, "usread": 1, "crm": 1, "experienceecommercemobile": 1}