{"oracle": 4, "ceo": 2, "mark": 2, "hurdthose": 1, "familiar": 1, "format": 1, "openworld": 2, "know": 2, "cofounder": 1, "cto": 1, "larry": 1, "ellison": 2, "keynote": 2, "tends": 1, "provide": 1, "nitty": 1, "gritty": 1, "technical": 1, "detail": 1, "future": 2, "technology": 2, "release": 1, "however": 2, "want": 2, "top": 1, "level": 2, "insight": 2, "direction": 1, "market": 5, "business": 1, "thinking": 1, "term": 1, "digital": 1, "buying": 1, "head": 1, "hurds": 1, "keynoteand": 1, "true": 2, "form": 1, "year": 7, "focused": 2, "security": 1, "autonomous": 2, "database": 1, "whilst": 2, "hurd": 5, "took": 2, "stage": 1, "geopolitical": 1, "fear": 1, "mongering": 1, "state": 1, "world": 2, "give": 2, "prediction": 12, "buyer": 2, "behaviour": 1, "first": 2, "fun": 2, "audience": 1, "taking": 1, "jab": 1, "analyst": 4, "industry": 1, "claim": 1, "slow": 1, "pick": 1, "ago": 2, "saidi": 1, "look": 1, "back": 1, "talk": 1, "made": 2, "three": 2, "hit": 1, "couple": 1, "production": 1, "apps": 2, "cloud": 6, "remember": 1, "two": 4, "saas": 1, "suite": 1, "provider": 1, "budget": 1, "spent": 2, "service": 2, "enterprise": 1, "secure": 1, "place": 1, "processingby": 1, "way": 3, "delivered": 1, "got": 1, "thought": 3, "unfair": 1, "criticism": 2, "people": 4, "nutty": 1, "didnt": 1, "make": 2, "sense": 1, "okayafter": 1, "showing": 1, "slide": 2, "showed": 1, "essentially": 1, "reflected": 1, "except": 1, "came": 1, "later": 1, "particular": 1, "friendly": 1, "jibe": 1, "gartner": 2, "said": 6, "tongue": 1, "firmly": 1, "cheeki": 1, "would": 2, "show": 1, "chart": 1, "saying": 2, "theyre": 4, "timeframe": 1, "could": 3, "told": 1, "incredible": 1, "wayi": 1, "love": 1, "gartnerif": 1, "ever": 1, "wonder": 1, "value": 1, "coming": 2, "advanced": 1, "subscribe": 1, "take": 1, "see": 2, "new": 1, "crediblelooking": 1, "forward": 1, "hed": 1, "finished": 1, "poking": 1, "go": 1, "deliver": 1, "time": 4, "maybe": 1, "taken": 2, "seriouslythey": 1, "mostly": 1, "increased": 1, "use": 1, "ai": 7, "automation": 1, "major": 1, "impact": 2, "productivity": 1, "innovationhurds": 1, "deeply": 1, "embedded": 1, "application": 4, "saidat": 1, "risk": 1, "im": 1, "going": 6, "right": 1, "include": 1, "integrated": 2, "blockchain": 2, "nonsense": 1, "separate": 1, "solution": 2, "youre": 2, "extract": 1, "data": 2, "send": 1, "called": 1, "thats": 1, "end": 1, "directly": 1, "themselvessecondly": 1, "result": 1, "almost": 1, "interaction": 2, "customer": 3, "automated": 3, "leaving": 1, "employee": 1, "focus": 1, "higher": 2, "engagement": 1, "today": 2, "everything": 1, "done": 5, "basically": 2, "trying": 1, "gather": 1, "real": 1, "something": 2, "measured": 1, "millisecond": 1, "need": 2, "thoughtful": 1, "engage": 1, "wont": 1, "deal": 1, "whats": 1, "problem": 1, "get": 4, "move": 1, "forwardand": 1, "finally": 1, "pointed": 1, "job": 6, "particularly": 1, "department": 1, "area": 1, "currently": 1, "added": 1, "invented": 1, "yet": 1, "sit": 1, "conference": 1, "hear": 1, "dba": 1, "may": 1, "disintermediated": 1, "tuning": 1, "typically": 1, "manually": 1, "elimination": 1, "free": 1, "work": 1, "order": 1, "task": 1, "automate": 1, "faster": 1, "better": 1, "thing": 1, "fasterautomation": 1, "replace": 1, "create": 1, "example": 1, "robot": 2, "supervisor": 1, "everyone": 1, "bos": 1, "including": 1, "ensures": 1, "bot": 1, "performing": 1, "expect": 1, "created": 1, "imagined": 1, "requires": 1, "freeing": 1, "applied": 1, "jobsmy": 1, "takeover": 1, "gartnerimage": 1, "credit": 1, "image": 1, "authordisclosure": 1, "diginomica": 1, "premier": 1, "partner": 1, "writing": 1, "read": 1, "platform": 1, "infrastructure": 1, "architectureiot": 1, "robotics": 1, "aimachine": 1, "intelligence": 1}