{"peter": 2, "coffeethe": 1, "word": 1, "technology": 7, "come": 2, "root": 1, "meaning": 1, "mean": 2, "gain": 1, "expression": 1, "thought": 1, "roll": 1, "around": 2, "head": 1, "moment": 1, "realize": 1, "implies": 1, "object": 2, "make": 2, "tool": 2, "knowledge": 4, "find": 3, "way": 2, "expressand": 1, "shareabout": 1, "transforming": 1, "natural": 1, "world": 5, "create": 1, "human": 2, "value": 1, "making": 1, "stuff": 2, "outcome": 1, "however": 2, "important": 1, "might": 2, "culture": 1, "enablesconsequently": 1, "mere": 1, "invention": 1, "requires": 2, "adoption": 1, "become": 1, "innovationthank": 1, "druckermere": 1, "effective": 1, "teacher": 1, "able": 1, "student": 1, "bring": 1, "forth": 2, "impactful": 1, "reason": 1, "talent": 2, "pipeline": 2, "must": 2, "primary": 1, "consideration": 1, "side": 1, "issue": 1, "anyone": 1, "tasked": 1, "turning": 1, "potential": 1, "new": 10, "science": 4, "practice": 1, "well": 2, "proud": 1, "pas": 1, "alongthe": 1, "especially": 1, "high": 3, "list": 1, "concern": 2, "time": 1, "every": 1, "year": 2, "season": 1, "many": 4, "u": 1, "school": 3, "hold": 1, "college": 3, "fair": 1, "event": 2, "aimed": 1, "answering": 1, "question": 2, "focusing": 1, "energy": 2, "teenager": 1, "parent": 1, "contemplating": 1, "option": 1, "university": 2, "education": 1, "subsequent": 1, "career": 2, "member": 1, "active": 1, "alumnus": 1, "network": 2, "often": 2, "participate": 1, "program": 1, "representative": 1, "particular": 1, "guest": 1, "speaker": 1, "general": 1, "study": 2, "expect": 1, "ill": 1, "learnwhen": 1, "given": 1, "chance": 1, "talk": 2, "soontobegraduates": 1, "take": 1, "position": 1, "course": 3, "catalog": 2, "function": 1, "like": 5, "rearview": 1, "mirror": 1, "overthehorizon": 1, "radar": 1, "there": 1, "entire": 1, "industry": 1, "built": 1, "model": 1, "picking": 1, "mechanical": 1, "engineering": 4, "taking": 1, "prescribed": 1, "combination": 1, "class": 1, "collecting": 1, "credential": 1, "expecting": 1, "define": 1, "even": 3, "guarantee": 1, "pathtoday": 1, "seems": 1, "dreadfully": 1, "obsolete": 1, "approach": 1, "difficult": 1, "domain": 3, "overwhelmed": 1, "accelerating": 1, "flow": 1, "applying": 1, "best": 1, "degree": 2, "today": 2, "provide": 1, "foundation": 1, "context": 1, "lifetime": 1, "seeking": 1, "incorporating": 1, "continually": 1, "evolving": 1, "definition": 1, "competencyone": 1, "history": 2, "art": 3, "defined": 1, "accumulation": 1, "compilation": 1, "past": 1, "accomplishment": 1, "shielded": 1, "disruption": 1, "im": 2, "describing": 2, "area": 1, "seeing": 1, "practitioner": 1, "look": 2, "familiar": 1, "surroundings": 1, "lens": 1, "viewed": 2, "quantitative": 1, "trend": 1, "unveiled": 1, "literary": 1, "analysis": 1, "neural": 1, "net": 1, "deconstruction": 1, "painting": 1, "activation": 1, "separately": 1, "representing": 1, "content": 2, "stylestem": 1, "steamfarther": 1, "spectrum": 1, "misconception": 1, "another": 1, "common": 1, "mistake": 1, "thinking": 1, "computer": 1, "software": 1, "acronym": 1, "stem": 1, "recall": 1, "broadly": 1, "conceived": 1, "range": 1, "mathematics": 1, "personally": 1, "camp": 1, "prefers": 1, "steam": 1, "addition": 1, "enumeration": 1, "breakthrough": 1, "made": 1, "breathtaking": 1, "pace": 1, "thing": 1, "atom": 1, "perhaps": 2, "bitsin": 1, "recent": 1, "round": 1, "next": 1, "cohort": 1, "freshman": 1, "ive": 1, "therefore": 2, "added": 1, "emphasis": 1, "oldest": 1, "field": 1, "extraordinary": 2, "progress": 1, "builder": 1, "blacksmith": 1, "alchemist": 1, "longstanding": 1, "icon": 1, "advancement": 2, "caveman": 1, "city": 1, "dweller": 1, "space": 1, "voyager": 1, "much": 1, "mit": 1, "example": 2, "civil": 1, "quite": 1, "literally": 1, "department": 1, "number": 4, "material": 3, "chemistry": 2, "thirty": 1, "recognized": 1, "discipline": 1, "seniority": 1, "established": 1, "subject": 1, "though": 1, "misperceived": 1, "stagnationin": 1, "structure": 2, "height": 1, "tallest": 1, "building": 2, "exponential": 1, "curve": 1, "mooreslaw": 1, "hockeystick": 1, "graph": 1, "microprocessorsin": 1, "additive": 1, "manufacturing": 1, "powerful": 1, "illuminating": 1, "label": 1, "printing": 1, "forming": 1, "metal": 1, "substance": 1, "component": 1, "mechanism": 1, "capability": 1, "efficiencyin": 1, "understanding": 1, "matter": 2, "behavior": 1, "fundamental": 1, "level": 1, "bringing": 1, "kind": 1, "topological": 1, "semimetals": 1, "may": 1, "open": 2, "pathway": 1, "robust": 1, "quantum": 1, "device": 1, "superconductorsall": 1, "depend": 1, "mastery": 1, "digital": 2, "process": 1, "simulation": 1, "precise": 1, "control": 1, "machine": 1, "sophisticated": 1, "modeling": 1, "interaction": 1, "observer": 1, "seduction": 1, "crucial": 1, "expertise": 1, "shortrange": 1, "reward": 1, "creating": 1, "entertainment": 1, "apps": 1, "performing": 1, "financial": 1, "legerdemainas": 1, "archetyped": 1, "actor": 1, "zachary": 1, "quinto": 1, "wall": 1, "street": 1, "drama": 1, "margin": 1, "call": 1, "far": 1, "recipient": 1, "concluding": 1, "really": 1, "changing": 1, "adding": 1, "speak": 1, "freely": 1, "money": 1, "considerably": 1, "attractivethe": 1, "current": 1, "generation": 1, "steamer": 1, "accept": 1, "personal": 1, "charge": 1, "mandate": 1, "convey": 1, "excitement": 1, "remaking": 1, "physical": 1, "young": 1, "people": 1, "embodyquite": 1, "literallythe": 1, "tomorrowimage": 1, "credit": 1, "freeimagescomcsongor": 1, "vargaread": 1, "crm": 1, "customer": 1, "experiencedevops": 1, "nosql": 1, "source": 1, "stackdigital": 1, "marketingdigital": 1, "enterprise": 1, "real": 1, "worldiot": 1, "robotics": 1, "aipartner": 1, "zonesalesforce": 1}