{"telco": 2, "carrier": 3, "get": 5, "rough": 1, "ride": 1, "among": 1, "peer": 1, "bit": 1, "id": 4, "like": 1, "give": 1, "shout": 1, "tmobile": 16, "usa": 1, "customer": 8, "experience": 6, "youve": 1, "read": 1, "story": 1, "youll": 1, "understand": 1, "theyre": 1, "ranked": 1, "satisfactionfrom": 1, "data": 4, "gathered": 1, "nielsenwhile": 1, "u": 2, "contracted": 1, "cell": 1, "guzzler": 1, "offered": 1, "best": 1, "deal": 1, "distance": 1, "colleague": 1, "verizon": 1, "att": 1, "wondered": 1, "country": 2, "coverage": 1, "never": 1, "experienced": 1, "problem": 4, "short": 3, "met": 2, "need": 1, "price": 1, "prepared": 1, "pay": 1, "post": 2, "sale": 4, "service": 10, "really": 2, "matterspost": 1, "experiencewhen": 1, "iphone": 2, "went": 2, "awol": 1, "florida": 1, "got": 1, "back": 2, "running": 1, "le": 1, "minute": 2, "replacement": 1, "phoneas": 1, "preparing": 1, "leave": 1, "contacted": 1, "explained": 3, "happening": 1, "asked": 2, "terminate": 1, "hard": 1, "offer": 1, "suspend": 1, "line": 1, "case": 3, "return": 2, "uswhen": 1, "subsequent": 1, "billing": 1, "query": 1, "chat": 1, "bot": 1, "system": 3, "resolved": 1, "relatively": 1, "easily": 1, "wasnt": 1, "perfect": 1, "good": 2, "enoughwhen": 1, "thing": 2, "go": 3, "wrongthe": 1, "cx": 3, "icing": 1, "cake": 1, "came": 1, "unlock": 4, "unlike": 1, "maintains": 1, "lock": 1, "network": 1, "requires": 2, "meet": 1, "bunch": 1, "arcane": 1, "criterion": 2, "possible": 1, "bypass": 1, "handing": 1, "job": 1, "third": 1, "party": 1, "princely": 1, "sum": 1, "bad": 1, "something": 2, "achieved": 1, "free": 2, "opted": 1, "identical": 1, "paid": 1, "serviceagain": 1, "circumstance": 1, "rep": 1, "checked": 1, "would": 1, "happen": 1, "wait": 2, "confirmatory": 1, "email": 2, "take": 1, "hour": 4, "apple": 3, "require": 1, "remote": 1, "phonein": 1, "didnt": 1, "work": 3, "waited": 1, "receiving": 1, "message": 1, "phone": 4, "remained": 2, "locked": 1, "waiting": 1, "another": 2, "two": 1, "day": 1, "made": 1, "difference": 1, "call": 4, "time": 4, "agent": 1, "walked": 1, "reset": 1, "routine": 1, "unhurried": 1, "professional": 1, "manner": 2, "availshe": 1, "escalated": 1, "discover": 1, "told": 2, "experiencing": 1, "sporadic": 1, "delay": 2, "said": 1, "unlocked": 2, "acknowledged": 1, "end": 2, "could": 1, "mean": 1, "mismatch": 1, "information": 1, "courtesy": 1, "convenience": 1, "see": 1, "workedat": 1, "point": 2, "bear": 1, "mind": 1, "person": 1, "working": 1, "remotely": 1, "cheerful": 2, "throughout": 1, "demonstrated": 1, "level": 1, "knowledge": 1, "normally": 1, "associate": 1, "genius": 1, "bar": 1, "even": 1, "far": 1, "ensure": 1, "international": 1, "outbound": 1, "dialing": 1, "uk": 1, "phonethe": 1, "following": 1, "morning": 1, "magically": 1, "still": 1, "technical": 1, "supervisor": 1, "called": 1, "agreed": 1, "check": 1, "statuscx": 1, "mattersin": 1, "advisory": 1, "session": 1, "constantly": 1, "school": 1, "people": 2, "matter": 1, "integral": 1, "part": 1, "remember": 1, "also": 1, "isnt": 1, "making": 1, "penny": 1, "doesnt": 1, "stop": 1, "walk": 1, "away": 2, "account": 1, "fulfills": 1, "interpretation": 1, "adage": 1, "ive": 1, "often": 2, "used": 1, "year": 1, "send": 1, "bring": 1, "backwhen": 1, "thats": 1, "executed": 1, "pleasant": 1, "helpful": 3, "bet": 1, "business": 1, "consideration": 1, "alternativeas": 1, "consumer": 1, "complain": 1, "provider": 2, "look": 1, "whole": 1, "rate": 1, "world": 1, "classit": 1, "help": 1, "center": 1, "know": 1, "enough": 1, "immediately": 1, "fond": 1, "saying": 1, "technology": 1, "enabler": 1, "care": 1, "forethought": 1, "make": 1, "context": 1, "well": 1, "designed": 1, "process": 1, "every": 1, "step": 1, "beyond": 1, "relationship": 1, "remains": 1, "courteous": 1, "wrong": 1, "theyve": 1, "tapped": 1, "visceral": 1, "life": 1, "long": 1, "memoryanyone": 1, "similar": 1, "please": 1, "share": 1, "love": 1, "great": 1, "storiesimage": 1, "credit": 1, "tmobileread": 1, "crm": 1, "experiencecustomer": 1, "managementuse": 1}