{"year": 1, "virgin": 10, "atlantic": 5, "differentiated": 1, "based": 2, "customer": 17, "experience": 17, "whilst": 1, "airline": 5, "early": 1, "thought": 1, "traveller": 1, "cared": 1, "cost": 3, "seat": 1, "continued": 1, "stick": 1, "brand": 3, "ethos": 2, "focused": 1, "making": 1, "flying": 4, "pleasurable": 1, "experienceas": 1, "frequent": 1, "flyer": 1, "member": 4, "loyalty": 4, "programme": 2, "ive": 1, "got": 2, "appreciation": 1, "attention": 1, "detail": 1, "give": 4, "journey": 9, "keen": 1, "sit": 1, "company": 4, "lead": 1, "week": 2, "microsofts": 1, "future": 1, "decoded": 1, "event": 1, "london": 1, "launching": 1, "new": 2, "immersive": 2, "digital": 5, "window": 2, "sale": 3, "teami": 1, "try": 3, "first": 2, "hand": 1, "involves": 1, "placing": 1, "google": 1, "smartphone": 1, "slid": 1, "preloaded": 1, "application": 3, "take": 1, "degree": 1, "virtual": 1, "tour": 3, "upper": 2, "class": 2, "passenger": 1, "creates": 1, "really": 8, "realistic": 1, "view": 1, "like": 2, "check": 1, "using": 4, "use": 2, "lounge": 1, "airport": 2, "throughout": 2, "itselfthe": 1, "equipping": 1, "team": 4, "apps": 1, "hope": 1, "able": 3, "differentiate": 2, "selling": 1, "corporate": 1, "client": 1, "picking": 1, "going": 2, "send": 1, "valuable": 1, "business": 1, "tousing": 1, "microsoft": 3, "wearable": 1, "device": 3, "wrist": 1, "separate": 1, "app": 4, "also": 3, "collected": 1, "data": 8, "went": 2, "minute": 1, "used": 1, "finesse": 1, "reallife": 1, "travelling": 1, "atlanticdebbie": 1, "hulme": 2, "head": 1, "explainedon": 1, "see": 2, "tracking": 1, "u": 7, "something": 3, "thats": 2, "exciting": 1, "interesting": 1, "get": 6, "real": 2, "time": 4, "around": 2, "emotional": 3, "reaction": 1, "youre": 1, "already": 3, "traditional": 2, "method": 2, "track": 1, "resonance": 1, "people": 3, "physical": 2, "trying": 1, "recreate": 1, "interestingit": 1, "enrich": 1, "trial": 3, "relevance": 1, "react": 2, "look": 2, "smooth": 3, "peak": 2, "particularly": 4, "quite": 1, "stressful": 1, "traditionally": 2, "looked": 1, "product": 5, "richer": 2, "insight": 5, "test": 3, "way": 4, "continue": 2, "thatthis": 1, "understand": 2, "feel": 4, "reacting": 1, "rather": 2, "telling": 1, "feeliteration": 1, "key": 1, "explained": 1, "benefit": 1, "partnering": 1, "importance": 2, "deploy": 1, "within": 2, "short": 1, "timeframe": 1, "saidwe": 1, "set": 1, "challenge": 2, "jointly": 1, "matter": 1, "here": 1, "getting": 2, "deploying": 1, "salesforce": 1, "important": 2, "stuff": 3, "put": 1, "front": 1, "learn": 2, "develop": 2, "customersreuben": 1, "arnold": 2, "svp": 1, "marketing": 1, "added": 4, "deployed": 2, "virtually": 1, "smartphones": 2, "tablet": 2, "kit": 2, "required": 1, "isnt": 1, "expensive": 3, "total": 1, "project": 1, "hasnt": 1, "saidbecause": 1, "technology": 2, "built": 1, "universal": 1, "doesnt": 1, "require": 1, "lot": 5, "heavy": 1, "giving": 1, "special": 1, "headset": 1, "sort": 1, "surface": 1, "quickly": 1, "dont": 2, "need": 1, "carry": 1, "familiar": 1, "interface": 1, "usethey": 1, "focus": 2, "talking": 1, "without": 1, "go": 1, "training": 1, "forth": 1, "effective": 1, "deploythe": 1, "dataarnold": 1, "explain": 1, "always": 4, "strong": 1, "ability": 1, "enhance": 2, "absolutely": 1, "essential": 1, "explainedtechnology": 1, "another": 1, "opportunity": 1, "describe": 1, "think": 4, "portability": 1, "mobility": 1, "tool": 1, "mean": 1, "much": 1, "easier": 1, "would": 1, "gone": 1, "two": 1, "dimensional": 1, "imagery": 1, "information": 1, "adequately": 1, "describes": 1, "fly": 1, "usdata": 1, "critical": 1, "done": 2, "mapping": 1, "research": 1, "looking": 1, "tried": 1, "saying": 1, "help": 2, "skin": 1, "bit": 2, "depthhulme": 1, "agreed": 1, "highly": 2, "valued": 1, "useful": 1, "group": 1, "engaged": 1, "iterate": 1, "improve": 1, "regularly": 1, "saidi": 1, "high": 1, "expectation": 1, "part": 1, "meet": 1, "testing": 1, "brave": 1, "enough": 1, "thing": 2, "everything": 1, "work": 1, "fine": 1, "long": 1, "move": 1, "onwith": 1, "little": 1, "rich": 1, "often": 1, "community": 2, "called": 1, "plane": 1, "talk": 1, "regular": 1, "flyersthey": 1, "record": 1, "video": 1, "footage": 1, "share": 1, "collaborative": 1, "starting": 1, "servicesread": 1, "crm": 1, "experienceuse": 1, "case": 1}