{"telecom": 1, "giant": 1, "virgin": 6, "medium": 1, "embark": 1, "huge": 4, "infrastructure": 1, "project": 3, "digging": 1, "trench": 1, "laid": 1, "endtoend": 1, "would": 2, "stretch": 1, "round": 1, "equator": 1, "connecting": 1, "another": 1, "four": 1, "million": 1, "home": 1, "ukaggy": 1, "dhillon": 7, "head": 1, "people": 6, "insight": 8, "mediasaysas": 1, "imagine": 1, "going": 1, "amount": 2, "change": 3, "planning": 2, "mode": 1, "think": 1, "hr": 10, "analytics": 11, "really": 2, "help": 3, "drive": 2, "strategyhr": 1, "quickly": 1, "become": 1, "indispensable": 1, "tool": 1, "becoming": 1, "one": 1, "five": 1, "pillar": 1, "even": 1, "though": 1, "team": 10, "set": 1, "year": 2, "agoyet": 1, "strong": 2, "servicing": 1, "employee": 2, "three": 2, "keen": 1, "demonstrate": 1, "thatyou": 1, "quite": 2, "lot": 4, "lean": 1, "number": 1, "large": 1, "organizationthe": 1, "first": 2, "look": 2, "absence": 7, "figure": 1, "could": 1, "begin": 1, "analysis": 2, "needed": 1, "locate": 1, "data": 9, "verify": 1, "clean": 1, "wasa": 1, "held": 1, "separate": 2, "system": 3, "core": 1, "oracle": 1, "talent": 1, "management": 1, "resourcingdespite": 1, "disparate": 1, "source": 2, "belief": 1, "barrier": 1, "starting": 1, "analyticsyou": 1, "dont": 1, "need": 1, "invest": 1, "integration": 1, "work": 4, "excela": 1, "high": 4, "proportion": 1, "medias": 1, "call": 2, "center": 4, "showed": 2, "engagement": 1, "low": 1, "attrition": 1, "rate": 5, "among": 1, "workforcewhile": 1, "clearly": 2, "fantastic": 1, "result": 1, "also": 3, "noted": 1, "average": 1, "day": 1, "financial": 1, "implication": 1, "company": 1, "expandswe": 1, "identified": 1, "particular": 1, "contact": 3, "particularly": 1, "went": 1, "business": 5, "datathere": 1, "feeling": 1, "didnt": 1, "sickness": 2, "problem": 1, "around": 1, "validating": 1, "themwhat": 1, "found": 1, "real": 2, "lack": 1, "knowledge": 1, "policy": 3, "lenient": 1, "industry": 1, "standardthrough": 1, "combination": 1, "tightening": 1, "educating": 1, "line": 1, "manager": 1, "introducing": 1, "champion": 2, "push": 1, "message": 1, "ensure": 1, "action": 1, "taken": 1, "fallin": 1, "dramatic": 1, "reduction": 1, "making": 2, "saving": 1, "according": 1, "dhillonthe": 1, "reason": 2, "successful": 1, "load": 1, "untapped": 1, "growing": 1, "leadership": 1, "saw": 1, "believed": 1, "itdhillon": 1, "stress": 1, "none": 1, "possible": 1, "without": 1, "right": 1, "environment": 1, "within": 1, "teameducationas": 1, "fairly": 1, "new": 1, "took": 1, "time": 1, "educate": 1, "partner": 3, "workshop": 1, "training": 2, "bid": 1, "make": 1, "part": 2, "everyday": 1, "language": 1, "hrinitially": 1, "focused": 1, "explaining": 1, "benefit": 1, "largely": 1, "presenting": 1, "case": 2, "study": 1, "example": 1, "successfully": 1, "appliedthe": 1, "second": 1, "program": 1, "covered": 1, "technical": 1, "aspect": 1, "creating": 1, "graph": 1, "visualization": 1, "effective": 1, "presentationsthe": 1, "able": 1, "existing": 1, "relationship": 2, "addswith": 1, "realized": 1, "cant": 1, "everything": 1, "used": 1, "already": 1, "existed": 1, "thing": 3, "measurable": 1, "outcomeaccording": 1, "trying": 1, "embed": 1, "ethosthe": 1, "next": 3, "u": 3, "opportunity": 1, "challenge": 3, "culture": 1, "communityits": 1, "aiming": 1, "incorporating": 1, "experience": 1, "recognition": 1, "scheme": 1, "nominating": 1, "agenda": 1, "including": 1, "recruitment": 1, "processwith": 1, "early": 1, "success": 1, "belt": 1, "thinking": 1, "delving": 1, "predictive": 1, "saysweve": 1, "concentrated": 1, "see": 1, "touch": 1, "thats": 1, "given": 1, "intangiblesread": 1, "analysisfuture": 1, "workhcm": 1, "digital": 1, "future": 1}