{"subscription": 10, "management": 4, "vendor": 5, "zuora": 11, "going": 4, "toptier": 1, "global": 4, "enterprise": 6, "latest": 1, "release": 3, "cloudbased": 1, "software": 2, "announced": 1, "today": 2, "coincide": 1, "annual": 2, "conference": 1, "san": 1, "franciscothe": 1, "new": 9, "product": 4, "target": 3, "multinational": 1, "business": 5, "currently": 1, "use": 1, "established": 1, "erp": 3, "sap": 3, "oracle": 3, "run": 1, "want": 3, "add": 1, "flexible": 2, "payasyougo": 3, "billing": 6, "option": 1, "monetize": 2, "additional": 1, "service": 1, "relationship": 1, "alongside": 2, "traditional": 5, "onetime": 1, "transaction": 3, "model": 7, "first": 3, "popularized": 1, "softwareasaservice": 2, "tech": 1, "industry": 2, "mainstream": 1, "say": 4, "tom": 1, "krackeler": 1, "vp": 1, "gm": 1, "productsweve": 1, "serving": 1, "saas": 3, "company": 7, "really": 4, "seeing": 1, "innovating": 1, "market": 6, "waysit": 1, "enterprisegrade": 1, "weve": 1, "built": 1, "go": 3, "opportunity": 3, "feel": 1, "solution": 1, "give": 2, "every": 2, "team": 1, "shared": 1, "view": 1, "customer": 4, "ability": 1, "everything": 1, "scale": 2, "operation": 1, "globally": 1, "set": 1, "capability": 2, "allow": 2, "manage": 1, "multiple": 2, "entity": 1, "zuorathat": 1, "combination": 1, "believe": 1, "uniquely": 1, "allows": 1, "u": 1, "large": 6, "clientszuora": 1, "four": 1, "main": 1, "element": 1, "designed": 1, "appeal": 1, "serve": 1, "enterprisesinsights": 1, "usage": 1, "metric": 3, "delivered": 1, "combined": 1, "financial": 1, "demographic": 1, "help": 4, "leader": 3, "analyze": 1, "subscriber": 1, "behavior": 1, "test": 1, "innovative": 1, "propositionssupport": 1, "different": 1, "charge": 1, "introduced": 1, "managed": 1, "without": 1, "disruption": 1, "backoffice": 2, "systemsbusiness": 1, "performance": 1, "dashboard": 1, "finance": 1, "track": 2, "subscribercentric": 1, "arr": 1, "churn": 1, "renewal": 1, "rate": 1, "data": 1, "providing": 1, "overview": 1, "revenue": 4, "linesrapid": 1, "deployment": 1, "easy": 1, "integration": 1, "cloud": 4, "application": 1, "crm": 1, "well": 1, "system": 4, "including": 2, "billion": 4, "marketa": 1, "report": 4, "mgi": 2, "researchreleased": 1, "yesterdayby": 1, "project": 1, "total": 2, "addressable": 1, "tam": 1, "worldwide": 1, "economy": 1, "tool": 1, "adopt": 1, "call": 1, "agile": 3, "monetization": 1, "platform": 3, "category": 1, "includes": 1, "nine": 1, "separate": 1, "type": 1, "financials": 4, "order": 1, "ecommerce": 1, "support": 1, "cpq": 1, "configurepricequote": 2, "contract": 2, "recognition": 2, "mediation": 1, "also": 2, "identifies": 1, "internet": 1, "thing": 1, "significant": 1, "factor": 1, "driving": 1, "spendingone": 1, "notable": 1, "finding": 2, "predominantly": 1, "phenomenon": 1, "find": 1, "represented": 1, "targeting": 1, "krackelerwe": 1, "see": 1, "multibillion": 1, "making": 1, "commitment": 1, "shift": 2, "delivery": 1, "theyre": 1, "responsive": 1, "package": 1, "proposition": 1, "buyersthose": 1, "inflexible": 1, "accommodate": 1, "provides": 1, "highvolume": 1, "deal": 1, "quoting": 1, "collection": 1, "process": 1, "subledger": 1, "sends": 1, "resulting": 1, "journal": 1, "back": 1, "recordtheres": 1, "big": 1, "guide": 1, "key": 1, "transition": 1, "krackelera": 1, "lot": 1, "effort": 1, "around": 1, "helping": 1, "make": 1, "journey": 1, "economyfor": 1, "cfo": 1, "trying": 1, "change": 1, "backwardlooking": 1, "accounting": 1, "function": 1, "real": 1, "value": 1, "architecturemy": 1, "takewhen": 1, "launched": 1, "preserve": 1, "nascent": 1, "even": 1, "didnt": 1, "place": 1, "landscape": 1, "changed": 1, "dramatically": 1, "spreading": 1, "industrythat": 1, "spread": 1, "extensive": 1, "plenty": 1, "competition": 1, "notably": 1, "quotetocash": 1, "apttus": 2, "recently": 1, "salesforceacquired": 1, "steelbrick": 1, "netsuite": 2, "financialforce": 2, "intacct": 1, "response": 1, "moved": 1, "upmarket": 1, "focusing": 1, "attention": 1, "offer": 1, "volume": 2, "high": 2, "frequency": 1, "problem": 2, "complex": 1, "sale": 1, "youll": 2, "specialist": 1, "like": 1, "managing": 1, "rapidly": 1, "changing": 1, "unless": 1, "already": 1, "builtinto": 1, "yourexisting": 1, "turnon": 1, "basis": 1, "estimate": 1, "worth": 1, "one": 1, "thats": 2, "growing": 1, "year": 1, "bad": 1, "segment": 1, "fairly": 1, "claim": 1, "fieldupdated": 1, "toclarify": 1, "commission": 1, "mgis": 1, "independent": 1, "research": 1, "studyimage": 1, "credit": 1, "feature": 1, "image": 1, "ice": 1, "z": 1, "blue": 1, "sky": 1, "clousds": 1, "jrografik": 1, "fotoliacomdisclosure": 1, "time": 1, "writing": 1, "salesforce": 1, "diginomica": 1, "premier": 1, "partner": 1, "read": 1, "supply": 1, "chaincrm": 1, "experiencedigital": 1, "transformation": 1, "frictionless": 1}